eazyetl/__init__.py
eazyetl/extract.py
eazyetl/load.py
eazyetl/transform.py
eazyetl-0.1.6.dist-info/licenses/LICENSE
eazyetl-0.1.6.dist-info/METADATA
eazyetl-0.1.6.dist-info/WHEEL
eazyetl-0.1.6.dist-info/top_level.txt
eazyetl-0.1.6.dist-info/RECORD
