Metadata-Version: 2.4
Name: eazyetl
Version: 0.1.6
Summary: eazyetl, an end-to-end ETL (Extract, Transform, Load) pipeline development package using pandas, requests, sqlalchemy, psycopg2-binary
Author-email: Denzel Kinyua <denzelkinyua11@gmail.com>
License-Expression: MIT
Requires-Python: >=3.7
License-File: LICENSE
Requires-Dist: pandas
Requires-Dist: requests
Requires-Dist: sqlalchemy
Requires-Dist: psycopg2-binary
Requires-Dist: numpy
Requires-Dist: openpyxl
Dynamic: license-file
